setup.py
src/ramdpy/__init__.py
src/ramdpy/function.py
src/ramdpy/list.py
src/ramdpy.egg-info/PKG-INFO
src/ramdpy.egg-info/SOURCES.txt
src/ramdpy.egg-info/dependency_links.txt
src/ramdpy.egg-info/not-zip-safe
src/ramdpy.egg-info/top_level.txt