Metadata-Version: 1.0
Name: ramdpy
Version: 0.1.2
Summary: A Python port of RamdaJS
Home-page: https://github.com/neilrussell6/ramdpy
Author: Neil Russell
Author-email: neilrussell6@gmail.com
License: BSD
Platform: UNKNOWN
